Metadata-Version: 1.0
Name: double-prob-dist
Version: 0.2
Summary: Gaussian and Binomial distributions
Home-page: UNKNOWN
Author: Eric Paskey
Author-email: UNKNOWN
License: UNKNOWN
Platform: UNKNOWN
